domauto/SC_PARAMETERS.py
domauto/__init__.py
domauto/classlib.py
domauto/clean_files.py
domauto/command_line.py
domauto/crawler.py
domauto/da_classlib.py
domauto/da_iolib.py
domauto/da_plotlib.py
domauto/domauto_test.py
domauto/iolib.py
domauto/plotlib.py
domauto/scp_plotter.py
domauto/status_plotter.py
domauto/web_maker.py
domauto/tests/test_crawl.py
domauto/tests/test_domauto.py
domauto-0.3.0a13.dist-info/METADATA
domauto-0.3.0a13.dist-info/WHEEL
domauto-0.3.0a13.dist-info/entry_points.txt
domauto-0.3.0a13.dist-info/top_level.txt
domauto-0.3.0a13.dist-info/RECORD
